TrajCompress/__init__.py
TrajCompress/assets/Sample.txt
TrajCompress/src/List_Points_2_List_Points.py
TrajCompress/src/__init__.py
TrajCompress/src/algorithms/Angular_batch.py
TrajCompress/src/algorithms/DOTS_batch.py
TrajCompress/src/algorithms/DP_batch.py
TrajCompress/src/algorithms/Dead_Reckoning_batch.py
TrajCompress/src/algorithms/OPERB_batch.py
TrajCompress/src/algorithms/OpeningWindow_batch.py
TrajCompress/src/algorithms/SQUISH_E_batch.py
TrajCompress/src/algorithms/STTrace_batch.py
TrajCompress/src/algorithms/TD_TR_batch.py
TrajCompress/src/algorithms/Uniform_batch.py
TrajCompress/src/algorithms/__init__.py
TrajCompress/src/algorithms/bottom_up_batch.py
TrajCompress/src/algorithms/interval_batch.py
TrajCompress/src/algorithms/threshold_batch.py
TrajCompress/src/basic_notion/DistFunc.py
TrajCompress/src/basic_notion/LineSimplify.py
TrajCompress/src/basic_notion/Point.py
TrajCompress/src/basic_notion/__init__.py
TrajCompress/utils/__init__.py
TrajCompress/utils/get_sample.py
TrajCompress/utils/read_data.py
TrajCompress-0.1.6.dist-info/LICENSE
TrajCompress-0.1.6.dist-info/METADATA
TrajCompress-0.1.6.dist-info/WHEEL
TrajCompress-0.1.6.dist-info/top_level.txt
TrajCompress-0.1.6.dist-info/RECORD
